fastapi_auth/__init__.py
fastapi_auth/settings.py
fastapi_auth/cli/__init__.py
fastapi_auth/cli/utils.py
fastapi_auth/cli/commands/__init__.py
fastapi_auth/cli/commands/permission.py
fastapi_auth/cli/commands/role.py
fastapi_auth/cli/commands/social.py
fastapi_auth/cli/commands/user.py
fastapi_auth/database/__init__.py
fastapi_auth/database/db.py
fastapi_auth/models/__init__.py
fastapi_auth/models/base.py
fastapi_auth/models/common.py
fastapi_auth/models/rbac.py
fastapi_auth/models/social_providers.py
fastapi_auth/models/user.py
fastapi_auth/repositories/__init__.py
fastapi_auth/repositories/rbac_repository.py
fastapi_auth/repositories/social_provider_repository.py
fastapi_auth/repositories/user_repository.py
fastapi_auth/routers/__init__.py
fastapi_auth/routers/v1/auth_router.py
fastapi_auth/schemas/social.py
fastapi_auth/schemas/user.py
fastapi_auth/services/__init__.py
fastapi_auth/services/rbac.py
fastapi_auth/services/user_service.py
fastapi_auth/services/social/__init__.py
fastapi_auth/services/social/github.py
fastapi_auth/services/social/google.py
fastapi_auth/utils/__init__.py
fastapi_auth/utils/jwt.py
fastapi_auth/utils/logging.py
fastapi_auth/utils/password.py
fastapi_auth/utils/decorators/validators.py
oblox_fastapi_auth-0.1.4.dist-info/METADATA
oblox_fastapi_auth-0.1.4.dist-info/WHEEL
oblox_fastapi_auth-0.1.4.dist-info/entry_points.txt
oblox_fastapi_auth-0.1.4.dist-info/RECORD
