Metadata-Version: 2.4
Name: oblox-fastapi-auth
Version: 0.1.4
Summary: A comprehensive authentication package for FastAPI applications with JWT, RBAC, and social auth support
Author: FastAPI Auth Contributors
License: MIT
Keywords: authentication,fastapi,jwt,oauth,rbac,social-auth
Classifier: Development Status :: 4 - Beta
Classifier: Framework :: FastAPI
Classifier: Intended Audience :: Developers
Classifier: License :: OSI Approved :: MIT License
Classifier: Programming Language :: Python :: 3
Classifier: Programming Language :: Python :: 3.11
Classifier: Programming Language :: Python :: 3.12
Requires-Python: >=3.11
Requires-Dist: aiomysql>=0.3.2
Requires-Dist: aiosmtplib>=5.0.0
Requires-Dist: aiosqlite>=0.20.0
Requires-Dist: alembic>=1.17.2
Requires-Dist: asyncpg>=0.31.0
Requires-Dist: bcrypt>=5.0.0
Requires-Dist: click>=8.1.0
Requires-Dist: cryptography>=43.0.0
Requires-Dist: fastapi[standard]>=0.128.0
Requires-Dist: httpx>=0.28.1
Requires-Dist: pydantic-extra-types>=2.11.0
Requires-Dist: pydantic-settings>=2.12.0
Requires-Dist: pyjwt>=2.10.1
Requires-Dist: rich>=13.0.0
Requires-Dist: sqlalchemy[asyncio]>=2.0.45
Requires-Dist: structlog>=25.5.0
